[{"categories":null,"contents":"We use quantum Monte Carlo simulations (QMC) at the microscale to develop effective descriptions of larger length scales.\n","permalink":"/about/","tags":null,"title":"About QMC-HAMM"},{"categories":null,"contents":null,"permalink":"/","tags":null,"title":"QMC-HAMM"},{"categories":null,"contents":" Pathak, Wagner. \u0026ldquo;A light weight regularization for wave function parameter gradients in quantum Monte Carlo\u0026rdquo; arXiv:2002.01434  ","permalink":"/publications/","tags":null,"title":"QMC-HAMM"},{"categories":null,"contents":null,"permalink":"/","tags":null,"title":"Syna Theme"},{"categories":null,"contents":null,"permalink":"/categories/","tags":null,"title":"Categories"},{"categories":null,"contents":null,"permalink":"/tags/","tags":null,"title":"Tags"}]